spike_recorder/__init__.py
spike_recorder/client.py
spike_recorder/version.py
spike_recorder/experiments/__init__.py
spike_recorder/experiments/app_runner.py
spike_recorder/experiments/iowa/__init__.py
spike_recorder/experiments/iowa/app.py
spike_recorder/experiments/iowa/data.py
spike_recorder/experiments/iowa/deck.py
spike_recorder/experiments/iowa/instructions_ui.py
spike_recorder/experiments/iowa/iowa_ui.py
spike_recorder/experiments/iowa/win_message_ui.py
spike_recorder/experiments/libet/__init__.py
spike_recorder/experiments/libet/app.py
spike_recorder/experiments/libet/clock.py
spike_recorder/experiments/libet/data.py
spike_recorder/experiments/libet/instructions_ui.py
spike_recorder/experiments/libet/libet_ui.py
spike_recorder/server/__init__.py
spike_recorder/server/_core.cpython-38-darwin.so
spike_recorder/server/libbass.dylib
spike_recorder/server/data/analysis.bmp
spike_recorder/server/data/analysis.svg
spike_recorder/server/data/analysiscrossed.bmp
spike_recorder/server/data/analysiscrossed.svg
spike_recorder/server/data/analysishigh.bmp
spike_recorder/server/data/ascii.bmp
spike_recorder/server/data/backward.bmp
spike_recorder/server/data/backward.svg
spike_recorder/server/data/backwardhigh.bmp
spike_recorder/server/data/bconnected-high.bmp
spike_recorder/server/data/bconnected.bmp
spike_recorder/server/data/bdisconnected-high.bmp
spike_recorder/server/data/bdisconnected.bmp
spike_recorder/server/data/bncconn.bmp
spike_recorder/server/data/bncconn.svg
spike_recorder/server/data/bncconnhigh.bmp
spike_recorder/server/data/bupdate-high.bmp
spike_recorder/server/data/bupdate.bmp
spike_recorder/server/data/calibratebtn-high.bmp
spike_recorder/server/data/calibratebtn-normal.bmp
spike_recorder/server/data/cancel-high.bmp
spike_recorder/server/data/cancel-normal.bmp
spike_recorder/server/data/ckboxoff.bmp
spike_recorder/server/data/ckboxon.bmp
spike_recorder/server/data/ckboxon.svg
spike_recorder/server/data/config.bmp
spike_recorder/server/data/config.svg
spike_recorder-0.3.3.data/data/src/spike_recorder.egg-info/PKG-INFO
spike_recorder-0.3.3.data/data/src/spike_recorder.egg-info/not-zip-safe
spike_recorder-0.3.3.dist-info/LICENSE
spike_recorder-0.3.3.dist-info/METADATA
spike_recorder-0.3.3.dist-info/WHEEL
spike_recorder-0.3.3.dist-info/entry_points.txt
spike_recorder-0.3.3.dist-info/top_level.txt
spike_recorder-0.3.3.dist-info/RECORD
