Metadata-Version: 2.1
Name: spike_recorder
Version: 0.3.3
Summary: Python bindings for the Backyard Brains Spike Recorder software.
Home-page: https://github.com/davidt0x/py-spike-recorder
Author: David Turner
Author-email: dmturner@princeton.edu
Maintainer: David Turner
Maintainer-email: dmturner@princeton.edu
License: BSD 3-Clause License
Platform: Any
Classifier: Topic :: Scientific/Engineering
Classifier: Intended Audience :: Science/Research
Classifier: Intended Audience :: Developers
Classifier: Operating System :: OS Independent
Classifier: License :: OSI Approved :: BSD License
Classifier: Programming Language :: Python
Classifier: Programming Language :: Python :: 3
Classifier: Programming Language :: Python :: 3.6
Classifier: Programming Language :: Python :: 3.7
Classifier: Programming Language :: Python :: 3.8
Classifier: Programming Language :: Python :: 3.9
Classifier: Development Status :: 1 - Planning
Requires-Python: >=3.6
Provides-Extra: test
Provides-Extra: dev
Provides-Extra: docs
